paymatesApi/__init__.py
paymatesApi/admin.py
paymatesApi/apps.py
paymatesApi/errors.py
paymatesApi/models.py
paymatesApi/serializers.py
paymatesApi/tests.py
paymatesApi/types.py
paymatesApi/urls.py
paymatesApi/utils.py
paymatesApi/views.py
paymatesApi-0.1.3.dist-info/LICENCE
paymatesApi-0.1.3.dist-info/METADATA
paymatesApi-0.1.3.dist-info/WHEEL
paymatesApi-0.1.3.dist-info/top_level.txt
paymatesApi-0.1.3.dist-info/RECORD
