Metadata-Version: 2.1
Name: paymatesApi
Version: 0.1.3
Summary: paymatesApi library is a REST API that consumes flutterwave API
Home-page: https://github.com/derrimugisha
Author: Derick Mugisha
Author-email: derrimugisha@gmail.com
License: MIT
Keywords: django flutterwave-payments
Platform: any
Classifier: Environment :: Web Environment
Classifier: Framework :: Django
Classifier: Intended Audience :: Developers
Classifier: License :: OSI Approved :: MIT License
Classifier: Operating System :: OS Independent
Classifier: Programming Language :: Python
Classifier: Programming Language :: Python :: 3.4
Classifier: Programming Language :: Python :: 3.5
Classifier: Programming Language :: Python :: 3.6
Classifier: Programming Language :: Python :: 3.7
Classifier: Programming Language :: Python :: 3.8
Classifier: Topic :: Software Development :: Libraries :: Python Modules
License-File: LICENCE
